setup.py
caps_lock.egg-info/PKG-INFO
caps_lock.egg-info/SOURCES.txt
caps_lock.egg-info/dependency_links.txt
caps_lock.egg-info/entry_points.txt
caps_lock.egg-info/top_level.txt
src/caps_lock/__init__.py
src/caps_lock/module.py
src/caps_lock/data/caps_off.svg
src/caps_lock/data/caps_on.svg
src/caps_lock/data/num_off.svg
src/caps_lock/data/num_on.svg