Metadata-Version: 1.0
Name: caps-lock
Version: 1.0
Summary: Keyboard Status Applet
Home-page: https://www.github.com/lemoce/caps-lock
Author: Leandro Cerencio
Author-email: cerencio@yahoo.com.br
License: UNKNOWN
Platform: UNKNOWN
